src/__init__.py
src/server-mcp.py
src/helpers/__init__.py
src/helpers/constants.py
src/helpers/event_analysis.py
src/helpers/failure_analysis.py
src/helpers/log_analysis.py
src/helpers/ml_persistence.py
src/helpers/resource_topology.py
src/helpers/semantic_search.py
src/helpers/utils.py
lumino_mcp_server-0.9.3.dist-info/METADATA
lumino_mcp_server-0.9.3.dist-info/WHEEL
lumino_mcp_server-0.9.3.dist-info/licenses/LICENSE
lumino_mcp_server-0.9.3.dist-info/RECORD
