Metadata-Version: 2.4
Name: lumino-mcp-server
Version: 0.9.3
Summary: An open source MCP server empowering SREs with intelligent observability, predictive analytics, and AI-driven automation across Kubernetes, OpenShift, and Tekton environments.
Project-URL: Homepage, https://github.com/spre-sre/lumino-mcp-server
Project-URL: Repository, https://github.com/spre-sre/lumino-mcp-server
Project-URL: Issues, https://github.com/spre-sre/lumino-mcp-server/issues
Author: Lumino Team
License-Expression: Apache-2.0
License-File: LICENSE
Keywords: ai,kubernetes,mcp,monitoring,observability,openshift,pipelines,sre,tekton
Classifier: Development Status :: 3 - Alpha
Classifier: Intended Audience :: Developers
Classifier: License :: OSI Approved :: Apache Software License
Classifier: Programming Language :: Python :: 3
Classifier: Programming Language :: Python :: 3.10
Classifier: Programming Language :: Python :: 3.11
Classifier: Programming Language :: Python :: 3.12
Requires-Python: >=3.10
Requires-Dist: aiohttp>=3.12.2
Requires-Dist: kubernetes>=32.0.1
Requires-Dist: mcp[cli]>=1.10.1
Requires-Dist: networkx>=3.0
Requires-Dist: numpy>=1.24.0
Requires-Dist: pandas>=2.0.0
Requires-Dist: prometheus-client>=0.22.0
Requires-Dist: pydantic>=2.11.5
Requires-Dist: python-dotenv>=1.1.0
Requires-Dist: pyyaml>=6.0.2
Requires-Dist: requests>=2.31.0
Requires-Dist: scikit-learn>=1.6.1
Requires-Dist: starlette>=0.30.0
Requires-Dist: uvicorn>=0.30.0
